db_dtypes/__init__.py
db_dtypes/core.py
db_dtypes/pandas_backports.py
db_dtypes/version.py
db_dtypes-1.2.0.dist-info/AUTHORS
db_dtypes-1.2.0.dist-info/LICENSE
db_dtypes-1.2.0.dist-info/METADATA
db_dtypes-1.2.0.dist-info/WHEEL
db_dtypes-1.2.0.dist-info/top_level.txt
db_dtypes-1.2.0.dist-info/RECORD
