Metadata-Version: 2.1
Name: db-dtypes
Version: 1.2.0
Summary: Pandas Data Types for SQL systems (BigQuery, Spanner)
Home-page: https://github.com/googleapis/python-db-dtypes-pandas
Author: The db-dtypes Authors
Author-email: googleapis-packages@google.com
Keywords: sql,pandas
Platform: Posix; MacOS X; Windows
Classifier: Development Status :: 5 - Production/Stable
Classifier: Intended Audience :: Developers
Classifier: License :: OSI Approved :: Apache Software License
Classifier: Programming Language :: Python
Classifier: Programming Language :: Python :: 3
Classifier: Programming Language :: Python :: 3.7
Classifier: Programming Language :: Python :: 3.8
Classifier: Programming Language :: Python :: 3.9
Classifier: Programming Language :: Python :: 3.10
Classifier: Programming Language :: Python :: 3.11
Classifier: Programming Language :: Python :: 3.12
Classifier: Operating System :: OS Independent
Classifier: Topic :: Database :: Front-Ends
Requires-Python: >=3.7
License-File: LICENSE
License-File: AUTHORS
Requires-Dist: packaging>=17.0
Requires-Dist: pandas>=0.24.2
Requires-Dist: pyarrow>=3.0.0
Requires-Dist: numpy>=1.16.6
